{
  "reel_id": "DWl_-2xigb7",
  "creator": "exploringlondon",
  "url": "https://www.instagram.com/reel/DWl_-2xigb7/",
  "caption": "Stumbled across this gorgeous coffee shop recently and the interiors will take you to outer space (perfect if you’ve recently watched @projecthailmary!) but the coffees are also delicious, they have dedicated work space and they even do £5.90 waffle bowls - the best sweet treat! 🧇\n\n📍 @bexcoffeeuk at @brunswicklondon, Unit 20, Brunswick Centre, WC1N 1AW\n⏰ Open 8am-8pm Mon to Sat, and 9am-6pm on Sundays\n\n#londoncoffeeshop #bexcoffee",
  "metadata": {
    "hashtags": [
      "londoncoffeeshop",
      "bexcoffee"
    ],
    "mentions": [
      "projecthailmary",
      "bexcoffeeuk",
      "brunswicklondon"
    ],
    "geo_locations": [
      "@bexcoffeeuk at @brunswicklondon, Unit 20, Brunswick Centre, WC1N 1AW"
    ],
    "pinned_places": [
      "@bexcoffeeuk at @brunswicklondon, Unit 20, Brunswick Centre, WC1N 1AW"
    ]
  },
  "transcription": {
    "text": "",
    "language": null,
    "duration_sec": 14.931875
  },
  "transcription_error": null,
  "generated_at": "2026-06-19T07:05:52.027Z"
}