{
  "reel_id": "C2KSMlfPo3j",
  "creator": "empty.japan",
  "url": "https://www.instagram.com/reel/C2KSMlfPo3j/",
  "caption": "You have been warned! You won’t be able to stop taking photos in this restaurant.\n\nServing several courses of what can be described as an Italian-Japanese fusion, the flavor and beauty of each dish in @arancino.kyoto is mind-blowing 😍\n\nLocated in the heart of Kyoto, right next to the Takase River, an extremely important Kyoto landmark that was used for transporting goods from the Edo period for over 300 years.\n\nLocation:\nKyoto, Nakagyo Ward, Ichinofunairicho, 537-9\n[ad]",
  "metadata": {
    "hashtags": [],
    "mentions": [
      "arancino.kyoto"
    ],
    "geo_locations": [],
    "pinned_places": []
  },
  "transcription": {
    "text": "Thanks for watching!",
    "language": "english",
    "duration_sec": 15.02475
  },
  "transcription_error": null,
  "generated_at": "2026-06-18T20:03:53.217Z"
}