{
  "reel_id": "Cs_SdBEOIAq",
  "creator": "empty.japan",
  "url": "https://www.instagram.com/reel/Cs_SdBEOIAq/",
  "caption": "Heavy rain 大雨 (Ooame) in Kyoto today ☔️\nHappy Friday everyone ☺️\nI am too lazy today to write any long texts 😂 but maybe that’s good? Do you prefer longer or shorter texts under these videos? 🧐",
  "metadata": {
    "hashtags": [],
    "mentions": [],
    "geo_locations": [],
    "pinned_places": []
  },
  "transcription": {
    "text": "",
    "language": null,
    "duration_sec": 5.596
  },
  "transcription_error": null,
  "generated_at": "2026-06-18T20:05:31.838Z"
}