{
  "reel_id": "CcLFiN2JrSQ",
  "creator": "dotzsoh-singapore",
  "url": "https://www.instagram.com/reel/CcLFiN2JrSQ/",
  "caption": "do you like Spring? ✨🌸🌸🌸💕✨ #istanbul #turkey #springvibes #dotzsoh #magnoliablossom \n.\n.\nvid @dotzsoh @dotzsoh2 \n#dotzsoh #palace #springflowers #土耳其",
  "metadata": {
    "hashtags": [
      "istanbul",
      "turkey",
      "springvibes",
      "dotzsoh",
      "magnoliablossom",
      "dotzsoh",
      "palace",
      "springflowers",
      "土耳其"
    ],
    "mentions": [
      "dotzsoh",
      "dotzsoh2"
    ],
    "geo_locations": [],
    "pinned_places": []
  },
  "transcription": {
    "text": "Ladies and gentlemen, her.",
    "language": "english",
    "duration_sec": 17.1595
  },
  "transcription_error": null,
  "generated_at": "2026-06-19T12:18:19.807Z"
}