{
  "reel_id": "CtJu6YlgXa7",
  "creator": "ladyandhersweetescapes",
  "url": "https://www.instagram.com/reel/CtJu6YlgXa7/",
  "caption": "So many reasons to love the newly opened public beach in Dubai:\n\n📍 Dubai Islands Beach in Deira, near Centara Mirage Resort\n\n✔️Free entry\n✔️Free use of sun loungers\n✔️Beautiful pavement \n✔️ Showers and changing rooms\n✔️ Ice cream and beverage stalls \n✔️ Pet-friendly\n✔️ Gorgeous sunset view\n\n⚠️ There are no food stalls at the moment, so pack some light bites from home.\n\nTag your beach buddies!\n\n#DubaiIslandsBeach #ladyandhersweetescapes #visitUAE #dubaiblogger #uaeblogger #travelblogger #pinayblogger #mydubai #dubai #visitdubai #DubaiReels #Thingstodoindubai #DubaiBeach  #DubaiDestinations",
  "metadata": {
    "hashtags": [
      "DubaiIslandsBeach",
      "ladyandhersweetescapes",
      "visitUAE",
      "dubaiblogger",
      "uaeblogger",
      "travelblogger",
      "pinayblogger",
      "mydubai",
      "dubai",
      "visitdubai",
      "DubaiReels",
      "Thingstodoindubai",
      "DubaiBeach",
      "DubaiDestinations"
    ],
    "mentions": [],
    "geo_locations": [
      "Dubai Islands Beach in Deira, near Centara Mirage Resort"
    ],
    "pinned_places": [
      "Dubai Islands Beach in Deira, near Centara Mirage Resort"
    ]
  },
  "transcription": {
    "text": "I need your love so bad Can't do what I'm asking for With all your love We ain't got nothing to lose No love, oh It's just principle",
    "language": "english",
    "duration_sec": 14.28025
  },
  "transcription_error": null,
  "generated_at": "2026-06-19T12:21:22.024Z"
}