{
  "reel_id": "DL7RNphP54t",
  "creator": "empty.japan",
  "url": "https://www.instagram.com/reel/DL7RNphP54t/",
  "caption": "If you asked me to describe Japan in just 3 words, for me it would be:\n\n1. Safety\n2. Food\n3. Discovery\n\nIf you are traveling around Japan, you’ll experience something new every single day. And the fact that Japan is so compact only adds to that. Everything is so accessible, yet every place feels like its own little world.\n\nWhat would your 3 words be?",
  "metadata": {
    "hashtags": [],
    "mentions": [],
    "geo_locations": [],
    "pinned_places": []
  },
  "transcription": {
    "text": "So I'll see you guys later. Bye guys. ",
    "language": "english",
    "duration_sec": 7.315688
  },
  "transcription_error": null,
  "generated_at": "2026-06-18T20:10:08.011Z"
}