{
  "reel_id": "DYg5mMlAU8C",
  "creator": "kseniia.journey-london-rexby",
  "url": "https://www.instagram.com/reel/DYg5mMlAU8C/",
  "caption": "Magnolia Bakery has arrived in London ✨\n\nYou can try the delicious Magnolia Bakery banana pudding  along with matcha 🍵 or cold brew ☕️ at Cafe Ciel \n\n📅 Tues–Sun, 10am–7pm (Until June 10)\n📍 Café Ciel at The OWO, Raffles London @cafeciel.ldn @raffleslondon.theowo @magnoliabakery with @londoncoffeeshops 😊\n\n📸 @kseniia.journey \n\n[press]\n#london #bakery #londonthingstodo #magnoliabakery",
  "metadata": {
    "hashtags": [
      "london",
      "bakery",
      "londonthingstodo",
      "magnoliabakery"
    ],
    "mentions": [
      "cafeciel.ldn",
      "raffleslondon.theowo",
      "magnoliabakery",
      "londoncoffeeshops",
      "kseniia.journey"
    ],
    "geo_locations": [
      "Café Ciel at The OWO, Raffles London @cafeciel.ldn @raffleslondon.theowo @magnoliabakery with @londoncoffeeshops 😊"
    ],
    "pinned_places": [
      "Café Ciel at The OWO, Raffles London @cafeciel.ldn @raffleslondon.theowo @magnoliabakery with @londoncoffeeshops 😊"
    ]
  },
  "transcription": {
    "text": "Hi, hi, hi Hi, hi, hi Ooh",
    "language": "english",
    "duration_sec": 13.678
  },
  "transcription_error": null,
  "generated_at": "2026-06-19T12:20:22.884Z"
}