{
  "reel_id": "DXzBOChjWEn",
  "creator": "thefloridaqueenie",
  "url": "https://www.instagram.com/reel/DXzBOChjWEn/",
  "caption": "Looking for things to do around Florida? Comment \"Guide\" and I'll send you my interactive Florida map and guide with over 1,000 spots to explore! I did the work for you so you can just hit the road without hours of research and stress!\n\nAnna Maria Island has my 🩵 When are you going? \n\n#annamariaisland #florida #floridalife #floridabeaches #beachgirl",
  "metadata": {
    "hashtags": [
      "annamariaisland",
      "florida",
      "floridalife",
      "floridabeaches",
      "beachgirl"
    ],
    "mentions": [],
    "geo_locations": [],
    "pinned_places": []
  },
  "transcription": {
    "text": "Thanks for watching!",
    "language": "english",
    "duration_sec": 6.251938
  },
  "transcription_error": null,
  "generated_at": "2026-06-18T20:14:22.314Z"
}