{
  "reel_id": "DZX9YhovWPb",
  "creator": "rometravelers",
  "url": "https://www.instagram.com/reel/DZX9YhovWPb/",
  "caption": "The name is Mama. Just Mama. 🍸\n\n72 hours. One baby. One very beautiful stay at @hoteldelavillerome @roccofortehotels. No sidekick, no backup, no one to hold the nappy bag except me.\n\nTurns out you don’t need a tuxedo or a sports car to feel like a spy. You just need a great hotel, a baby who naps on cue, and the audacity to travel solo with a one year old.\n\nMission? Absolutely accomplished. 🇮🇹✨",
  "metadata": {
    "hashtags": [],
    "mentions": [
      "hoteldelavillerome",
      "roccofortehotels."
    ],
    "geo_locations": [],
    "pinned_places": []
  },
  "transcription": {
    "text": "",
    "language": null,
    "duration_sec": 36.572875
  },
  "transcription_error": null,
  "generated_at": "2026-06-18T17:18:58.773Z"
}