{
  "reel_id": "DNi_ZgZy1tt",
  "creator": "blacktravelpin",
  "url": "https://www.instagram.com/reel/DNi_ZgZy1tt/",
  "caption": "Rule Nr. 1 - Never listen to the doubters 😂😭\n\nFollow @blacktravelpin for more Daily Dubai Vibes. 😍 \n\n#dubai #dubaiproblems #dubailife #dubaitravel #travelmoments #travellife #dubaiproblems #dubaitrip #visitdubai #exploreuae #habibicometodubai",
  "metadata": {
    "hashtags": [
      "dubai",
      "dubaiproblems",
      "dubailife",
      "dubaitravel",
      "travelmoments",
      "travellife",
      "dubaiproblems",
      "dubaitrip",
      "visitdubai",
      "exploreuae",
      "habibicometodubai"
    ],
    "mentions": [
      "blacktravelpin"
    ],
    "geo_locations": [],
    "pinned_places": []
  },
  "transcription": {
    "text": "This video is for my geography teacher, who said that I will never go anywhere in life. Look at now, Eiffel Tower, Italy.",
    "language": "english",
    "duration_sec": 13.07425
  },
  "transcription_error": null,
  "generated_at": "2026-06-19T12:16:52.461Z"
}