{
  "reel_id": "C9mvBusPIbC",
  "creator": "ladyandhersweetescapes",
  "url": "https://www.instagram.com/reel/C9mvBusPIbC/",
  "caption": "Core memory! 💛\n\nIt’s been 6 months since my last post; my longest social media hiatus to date. Thanks to everyone who stayed and sent me lovely messages. 😘 \n\nI have so many stories to tell that I don’t know where to start. So, let me share this family reel that we created last May first. \n\nCatch up soon! 💗\n\n#family #Dubai #UAE  #ladyandhersweetescapes #dubaireels",
  "metadata": {
    "hashtags": [
      "family",
      "Dubai",
      "UAE",
      "ladyandhersweetescapes",
      "dubaireels"
    ],
    "mentions": [],
    "geo_locations": [],
    "pinned_places": []
  },
  "transcription": {
    "text": "Cause no matter if our blue skies turn to grey There's a ray of sun that's bound to light our way",
    "language": "english",
    "duration_sec": 9.173313
  },
  "transcription_error": null,
  "generated_at": "2026-06-19T12:20:49.504Z"
}