{
  "reel_id": "C5f-JdkPH3x",
  "creator": "empty.japan",
  "url": "https://www.instagram.com/reel/C5f-JdkPH3x/",
  "caption": "No one around, just birds singing and the sound of the approaching train... The comforting glow of the street lights. Sometimes the true beauty of life is in the most simple moments.",
  "metadata": {
    "hashtags": [],
    "mentions": [],
    "geo_locations": [],
    "pinned_places": []
  },
  "transcription": {
    "text": ".",
    "language": "english",
    "duration_sec": 8.012313
  },
  "transcription_error": null,
  "generated_at": "2026-06-18T20:04:25.740Z"
}