{
  "reel_id": "DYlVk2IRcYs",
  "creator": "kristinacors",
  "url": "https://www.instagram.com/reel/DYlVk2IRcYs/",
  "caption": "This is the perfect restaurant for date night in the Hamptons #travelbucketlist #thehamptons #summerinthehamptons #bestrestaurants #thingstodointhehamptons",
  "metadata": {
    "hashtags": [
      "travelbucketlist",
      "thehamptons",
      "summerinthehamptons",
      "bestrestaurants",
      "thingstodointhehamptons"
    ],
    "mentions": [],
    "geo_locations": [],
    "pinned_places": []
  },
  "transcription": {
    "text": "🎶 Music Outro 🎶",
    "language": "english",
    "duration_sec": 7.408563
  },
  "transcription_error": null,
  "generated_at": "2026-06-19T07:14:07.557Z"
}